superopt/__init__.py
superopt/optimizer.py
superopt/stability.py
superopt/supercontroller.py
superopt/supermem.py
superopt/superprompt.py
superopt/superrag.py
superopt/superreflexion.py
superopt/adapters/__init__.py
superopt/adapters/aider_adapter.py
superopt/adapters/base.py
superopt/adapters/codex_adapter.py
superopt/adapters/letta_adapter.py
superopt/comparison/__init__.py
superopt/comparison/ace_comparison.py
superopt/comparison/ace_data_processor.py
superopt/comparison/dataset_loaders.py
superopt/comparison/framework.py
superopt/comparison/gepa_adapter.py
superopt/comparison/gepa_comparison.py
superopt/comparison/models.py
superopt/core/__init__.py
superopt/core/environment.py
superopt/core/nlg.py
superopt/core/trace.py
superopt/evaluation/__init__.py
superopt/evaluation/metrics.py
superopt/rag/__init__.py
superopt/rag/lancedb_integration.py
superopt/rag/lancedb_store.py
superopt-0.1.1.dist-info/METADATA
superopt-0.1.1.dist-info/WHEEL
superopt-0.1.1.dist-info/licenses/LICENSE
superopt-0.1.1.dist-info/RECORD
