Metadata-Version: 2.4
Name: superopt
Version: 0.1.1
Summary: Agentic Environment Optimization for Autonomous AI Agents
Project-URL: Homepage, https://github.com/SuperagenticAI/superopt
Project-URL: Documentation, https://github.com/SuperagenticAI/superopt#readme
Project-URL: Repository, https://github.com/SuperagenticAI/superopt
Project-URL: Issues, https://github.com/SuperagenticAI/superopt/issues
Project-URL: Changelog, https://github.com/SuperagenticAI/superopt/blob/main/CHANGELOG.md
Author-email: Shashi Jagtap <shashi@super-agentic.ai>, Shashi Jagtap <shashikant.jagtap@icloud.com>
Maintainer-email: Shashi Jagtap <team@super-agentic.ai>, Shashi Jagtap <shashikant.jagtap@icloud.com>
License-Expression: Apache-2.0
License-File: LICENSE
Keywords: agents,ai,autonomous,llm,natural-language-gradients,optimization,prompts
Classifier: Development Status :: 3 - Alpha
Classifier: Intended Audience :: Developers
Classifier: Intended Audience :: Science/Research
Classifier: License :: OSI Approved :: Apache Software License
Classifier: Operating System :: OS Independent
Classifier: Programming Language :: Python :: 3
Classifier: Programming Language :: Python :: 3.12
Classifier: Programming Language :: Python :: 3.13
Classifier: Topic :: Scientific/Engineering :: Artificial Intelligence
Classifier: Topic :: Software Development :: Libraries :: Python Modules
Classifier: Typing :: Typed
Requires-Python: >=3.12
Requires-Dist: pydantic>=2.0.0
Provides-Extra: aider
Requires-Dist: backoff>=2.2.0; extra == 'aider'
Requires-Dist: beautifulsoup4>=4.14.0; extra == 'aider'
Requires-Dist: configargparse>=1.7.0; extra == 'aider'
Requires-Dist: diff-match-patch>=20241021; extra == 'aider'
Requires-Dist: diskcache>=5.6.0; extra == 'aider'
Requires-Dist: gitpython>=3.1.0; extra == 'aider'
Requires-Dist: grep-ast>=0.9.0; extra == 'aider'
Requires-Dist: importlib-metadata<8.0.0; extra == 'aider'
Requires-Dist: importlib-resources>=6.5.0; extra == 'aider'
Requires-Dist: json5>=0.12.0; extra == 'aider'
Requires-Dist: jsonschema>=4.0.0; extra == 'aider'
Requires-Dist: litellm>=1.80.0; extra == 'aider'
Requires-Dist: mixpanel>=5.0.0; extra == 'aider'
Requires-Dist: networkx<3.5; extra == 'aider'
Requires-Dist: oslex>=0.1.0; extra == 'aider'
Requires-Dist: packaging>=25.0; extra == 'aider'
Requires-Dist: pathspec>=0.12.0; extra == 'aider'
Requires-Dist: pexpect>=4.9.0; extra == 'aider'
Requires-Dist: pillow>=12.0.0; extra == 'aider'
Requires-Dist: posthog>=7.0.0; extra == 'aider'
Requires-Dist: prompt-toolkit>=3.0.0; extra == 'aider'
Requires-Dist: psutil>=7.1.0; extra == 'aider'
Requires-Dist: pydub>=0.25.0; extra == 'aider'
Requires-Dist: pypandoc>=1.16.0; extra == 'aider'
Requires-Dist: pyperclip>=1.11.0; extra == 'aider'
Requires-Dist: pyyaml>=6.0.0; extra == 'aider'
Requires-Dist: rich>=14.0.0; extra == 'aider'
Requires-Dist: scipy<1.16; extra == 'aider'
Requires-Dist: shtab>=1.8.0; extra == 'aider'
Requires-Dist: socksio>=1.0.0; extra == 'aider'
Requires-Dist: watchfiles>=1.1.0; extra == 'aider'
Provides-Extra: all
Requires-Dist: backoff>=2.2.0; extra == 'all'
Requires-Dist: beautifulsoup4>=4.14.0; extra == 'all'
Requires-Dist: black>=23.0.0; extra == 'all'
Requires-Dist: configargparse>=1.7.0; extra == 'all'
Requires-Dist: diff-match-patch>=20241021; extra == 'all'
Requires-Dist: diskcache>=5.6.0; extra == 'all'
Requires-Dist: gitpython>=3.1.0; extra == 'all'
Requires-Dist: grep-ast>=0.9.0; extra == 'all'
Requires-Dist: importlib-metadata<8.0.0; extra == 'all'
Requires-Dist: importlib-resources>=6.5.0; extra == 'all'
Requires-Dist: json5>=0.12.0; extra == 'all'
Requires-Dist: jsonschema>=4.0.0; extra == 'all'
Requires-Dist: lancedb>=0.26.0; extra == 'all'
Requires-Dist: litellm>=1.80.0; extra == 'all'
Requires-Dist: mixpanel>=5.0.0; extra == 'all'
Requires-Dist: mypy>=1.0.0; extra == 'all'
Requires-Dist: networkx<3.5; extra == 'all'
Requires-Dist: oslex>=0.1.0; extra == 'all'
Requires-Dist: packaging>=25.0; extra == 'all'
Requires-Dist: pathspec>=0.12.0; extra == 'all'
Requires-Dist: pexpect>=4.9.0; extra == 'all'
Requires-Dist: pillow>=12.0.0; extra == 'all'
Requires-Dist: posthog>=7.0.0; extra == 'all'
Requires-Dist: pre-commit>=3.0.0; extra == 'all'
Requires-Dist: prompt-toolkit>=3.0.0; extra == 'all'
Requires-Dist: psutil>=7.1.0; extra == 'all'
Requires-Dist: pydub>=0.25.0; extra == 'all'
Requires-Dist: pypandoc>=1.16.0; extra == 'all'
Requires-Dist: pyperclip>=1.11.0; extra == 'all'
Requires-Dist: pytest-cov>=4.0.0; extra == 'all'
Requires-Dist: pytest>=7.0.0; extra == 'all'
Requires-Dist: pyyaml>=6.0.0; extra == 'all'
Requires-Dist: rich>=14.0.0; extra == 'all'
Requires-Dist: ruff>=0.1.0; extra == 'all'
Requires-Dist: scipy<1.16; extra == 'all'
Requires-Dist: sentence-transformers>=2.2.0; extra == 'all'
Requires-Dist: shtab>=1.8.0; extra == 'all'
Requires-Dist: socksio>=1.0.0; extra == 'all'
Requires-Dist: watchfiles>=1.1.0; extra == 'all'
Provides-Extra: dev
Requires-Dist: black>=23.0.0; extra == 'dev'
Requires-Dist: mypy>=1.0.0; extra == 'dev'
Requires-Dist: pre-commit>=3.0.0; extra == 'dev'
Requires-Dist: pytest-cov>=4.0.0; extra == 'dev'
Requires-Dist: pytest>=7.0.0; extra == 'dev'
Requires-Dist: ruff>=0.1.0; extra == 'dev'
Provides-Extra: lancedb
Requires-Dist: lancedb>=0.26.0; extra == 'lancedb'
Requires-Dist: sentence-transformers>=2.2.0; extra == 'lancedb'
